{
  "$schema": "https://json-schema.org/draft/2020-12/schema",
  "title": "Events",
  "description": "A description of application events to be triggered",
  "type": "object",
  "additionalProperties": false,
  "properties": {
    "application": {
      "$ref": "common/events/application.schema.json"
    },
    "load": {
      "$ref": "common/events/load.schema.json"
    },
    "unload": {
      "$ref": "common/events/unload.schema.json"
    },
    "transition": {
      "$ref": "common/events/transition.schema.json"
    },
    "set": {
      "$ref": "common/events/set.schema.json"
    },
    "call_service": {
      "$ref": "common/events/call_service.schema.json"
    },
    "lifecycle": {
      "$ref": "common/events/lifecycle.schema.json"
    },
    "switch_controllers": {
      "$ref": "common/events/switch_controllers.schema.json"
    },
    "sequence": {
      "$ref": "common/events/sequence.schema.json"
    }
  }
}